pdcatcontext/__init__.py
pdcatcontext/_cat_context.py
pdcatcontext/_pointer.py
pdcatcontext/_utils.py
pdcatcontext/custom_methods/__init__.py
pdcatcontext/custom_methods/_series_add.py
pdcatcontext-0.1.0.dist-info/licenses/LICENSE
tests/__init__.py
tests/test_add.py
tests/test_categorize_and_unify.py
tests/test_init.py
pdcatcontext-0.1.0.dist-info/METADATA
pdcatcontext-0.1.0.dist-info/WHEEL
pdcatcontext-0.1.0.dist-info/top_level.txt
pdcatcontext-0.1.0.dist-info/RECORD
